mmaction/__init__.py
mmaction/version.py
mmaction/apis/__init__.py
mmaction/apis/inference.py
mmaction/apis/test.py
mmaction/apis/train.py
mmaction/core/__init__.py
mmaction/core/dist_utils.py
mmaction/core/evaluation/__init__.py
mmaction/core/evaluation/accuracy.py
mmaction/core/evaluation/eval_hooks.py
mmaction/core/fp16/__init__.py
mmaction/core/fp16/decorators.py
mmaction/core/fp16/hooks.py
mmaction/core/fp16/utils.py
mmaction/core/optimizer/__init__.py
mmaction/core/optimizer/copy_of_sgd.py
mmaction/core/optimizer/tsm_optimizer_constructor.py
mmaction/datasets/__init__.py
mmaction/datasets/activitynet_dataset.py
mmaction/datasets/base.py
mmaction/datasets/builder.py
mmaction/datasets/dataset_wrappers.py
mmaction/datasets/rawframe_dataset.py
mmaction/datasets/registry.py
mmaction/datasets/video_dataset.py
mmaction/datasets/pipelines/__init__.py
mmaction/datasets/pipelines/augmentations.py
mmaction/datasets/pipelines/compose.py
mmaction/datasets/pipelines/formating.py
mmaction/datasets/pipelines/loading.py
mmaction/datasets/samplers/__init__.py
mmaction/datasets/samplers/distributed_sampler.py
mmaction/localization/__init__.py
mmaction/localization/bsn_utils.py
mmaction/localization/proposal_utils.py
mmaction/models/__init__.py
mmaction/models/builder.py
mmaction/models/registry.py
mmaction/models/backbones/__init__.py
mmaction/models/backbones/resnet.py
mmaction/models/backbones/resnet2plus1d.py
mmaction/models/backbones/resnet3d.py
mmaction/models/backbones/resnet3d_slowfast.py
mmaction/models/backbones/resnet3d_slowonly.py
mmaction/models/backbones/resnet_tsm.py
mmaction/models/common/__init__.py
mmaction/models/common/conv2plus1d.py
mmaction/models/heads/__init__.py
mmaction/models/heads/base.py
mmaction/models/heads/i3d_head.py
mmaction/models/heads/slowfast_head.py
mmaction/models/heads/tsm_head.py
mmaction/models/heads/tsn_head.py
mmaction/models/localizers/__init__.py
mmaction/models/localizers/base.py
mmaction/models/localizers/bmn.py
mmaction-0.5.0.dist-info/LICENSE
mmaction-0.5.0.dist-info/METADATA
mmaction-0.5.0.dist-info/WHEEL
mmaction-0.5.0.dist-info/top_level.txt
mmaction-0.5.0.dist-info/RECORD
