Metadata-Version: 2.1
Name: mmaction
Version: 0.5.0
Summary: OpenMMLab Action Understanding Toolbox and Benchmark
Home-page: https://github.com/open-mmlab/mmaction2
Maintainer: MMAction Authors
Maintainer-email: openmmlab@gmail.com
License: Apache License 2.0
Platform: UNKNOWN
Classifier: Development Status :: 4 - Beta
Classifier: License :: OSI Approved :: Apache Software License
Classifier: Operating System :: OS Independent
Classifier: Programming Language :: Python :: 3
Classifier: Programming Language :: Python :: 3.5
Classifier: Programming Language :: Python :: 3.6
Classifier: Programming Language :: Python :: 3.7
Requires-Dist: matplotlib
Requires-Dist: mmcv
Requires-Dist: numpy
Requires-Dist: opencv-contrib-python
Requires-Dist: Pillow (<=6.2.2)
Provides-Extra: all
Requires-Dist: numpy ; extra == 'all'
Requires-Dist: torch (>=1.3) ; extra == 'all'
Requires-Dist: av ; extra == 'all'
Requires-Dist: decord ; extra == 'all'
Requires-Dist: PyTurboJPEG ; extra == 'all'
Requires-Dist: matplotlib ; extra == 'all'
Requires-Dist: mmcv ; extra == 'all'
Requires-Dist: opencv-contrib-python ; extra == 'all'
Requires-Dist: Pillow (<=6.2.2) ; extra == 'all'
Requires-Dist: coverage ; extra == 'all'
Requires-Dist: flake8 ; extra == 'all'
Requires-Dist: interrogate ; extra == 'all'
Requires-Dist: isort (==4.3.21) ; extra == 'all'
Requires-Dist: pytest ; extra == 'all'
Requires-Dist: pytest-runner ; extra == 'all'
Requires-Dist: xdoctest (>=0.10.0) ; extra == 'all'
Requires-Dist: yapf ; extra == 'all'
Provides-Extra: build
Requires-Dist: numpy ; extra == 'build'
Requires-Dist: torch (>=1.3) ; extra == 'build'
Provides-Extra: optional
Requires-Dist: av ; extra == 'optional'
Requires-Dist: decord ; extra == 'optional'
Requires-Dist: PyTurboJPEG ; extra == 'optional'
Provides-Extra: tests
Requires-Dist: coverage ; extra == 'tests'
Requires-Dist: flake8 ; extra == 'tests'
Requires-Dist: interrogate ; extra == 'tests'
Requires-Dist: isort (==4.3.21) ; extra == 'tests'
Requires-Dist: pytest ; extra == 'tests'
Requires-Dist: pytest-runner ; extra == 'tests'
Requires-Dist: xdoctest (>=0.10.0) ; extra == 'tests'
Requires-Dist: yapf ; extra == 'tests'
